py_jwt_verifier/__init__.py
py_jwt_verifier/exceptions.py
py_jwt_verifier/jwk.py
py_jwt_verifier/jwt.py
py_jwt_verifier/utils.py
py_jwt_verifier/verifier.py
py_jwt_verifier/jws/__init__.py
py_jwt_verifier/jws/base.py
py_jwt_verifier/jws/rs256.py
py_jwt_verifier-0.8.0.dist-info/LICENSE
py_jwt_verifier-0.8.0.dist-info/METADATA
py_jwt_verifier-0.8.0.dist-info/WHEEL
py_jwt_verifier-0.8.0.dist-info/top_level.txt
py_jwt_verifier-0.8.0.dist-info/RECORD
