Metadata-Version: 2.1
Name: py_jwt_verifier
Version: 0.8.0
Summary: Python JWT Verfier - Verifies the signature of a digitally signed JWT.
Home-page: https://github.com/adrianlzr/py-jwt-verifier
Author: Adrian Lazar
Author-email: adrian.lazar95@outlook.com
License: MIT
Project-URL: Documentation & Source, https://github.com/adrianlzr/py-jwt-verifier
Project-URL: Issue Tracker, https://github.com/adrianlzr/py-jwt-verifier/issues
Keywords: python jwt verifier,jwt verifier,jwt signature verifier,py-jwt-verifier,python-jwt-verifier,python jwt signature verifier
Classifier: Programming Language :: Python :: 3
Classifier: Programming Language :: Python :: 3.8
Classifier: Programming Language :: Python :: 3.9
Classifier: Programming Language :: Python :: 3.10
Classifier: Programming Language :: Python :: 3.11
Classifier: Programming Language :: Python :: 3.12
Classifier: License :: OSI Approved :: MIT License
Classifier: Operating System :: OS Independent
Classifier: Development Status :: 5 - Production/Stable
Classifier: Topic :: Security :: Cryptography 
Requires-Python: >=3.8.0
License-File: LICENSE
Requires-Dist: requests <2.40.0,>=2.31.0
Requires-Dist: requests-cache <1.3.0,>=1.2.0
Requires-Dist: urllib3 >=2.0
